sfs-da/SFS_DA.py
sfs-da/__init__.py
sfs-da/conditioning.py
sfs-da/generate.py
sfs-da/pivot.py
sfs-da/util.py
sfs_da/SFS_DA.py
sfs_da/__init__.py
sfs_da/conditioning.py
sfs_da/generate.py
sfs_da/pivot.py
sfs_da/util.py
sfs_da-1.0.4.dist-info/METADATA
sfs_da-1.0.4.dist-info/WHEEL
sfs_da-1.0.4.dist-info/top_level.txt
sfs_da-1.0.4.dist-info/RECORD
