Metadata-Version: 2.1
Name: sfs_da
Version: 1.0.4
Summary: A package for Statistical Inference for Feature Selection after OT-based Domain Adaptation
Home-page: https://github.com/NT-Loi/SFS_DA.git
Author: Nguyen Thang Loi
Author-email: 23520872@gm.uit.edu.vn
License: MIT
Requires-Dist: numpy
Requires-Dist: mpmath
Requires-Dist: scipy
Requires-Dist: scikit-learn
